odoo8_addon_product_variant_storage_location-8.0.1.0.0-py2.7-nspkg.pth
odoo8_addon_product_variant_storage_location-8.0.1.0.0.dist-info/DESCRIPTION.rst
odoo8_addon_product_variant_storage_location-8.0.1.0.0.dist-info/METADATA
odoo8_addon_product_variant_storage_location-8.0.1.0.0.dist-info/RECORD
odoo8_addon_product_variant_storage_location-8.0.1.0.0.dist-info/WHEEL
odoo8_addon_product_variant_storage_location-8.0.1.0.0.dist-info/metadata.json
odoo8_addon_product_variant_storage_location-8.0.1.0.0.dist-info/namespace_packages.txt
odoo8_addon_product_variant_storage_location-8.0.1.0.0.dist-info/top_level.txt
odoo_addons/product_variant_storage_location/README.rst
odoo_addons/product_variant_storage_location/__init__.py
odoo_addons/product_variant_storage_location/__openerp__.py
odoo_addons/product_variant_storage_location/product.py
odoo_addons/product_variant_storage_location/images/product_storage_location.png
odoo_addons/product_variant_storage_location/static/description/icon.png
odoo_addons/product_variant_storage_location/tests/__init__.py
odoo_addons/product_variant_storage_location/tests/test_product.py
